hdao/__init__.py
hdao/hdao_cdc_op.py
hdao/hdao_events.py
hdao/hdao_price_feeder.py
hdao/hx_wallet_api.py
hdao/utils.py
tests/__init__.py
tests/config.py
tests/hx_testnet.py
tests/test_cdc_op.py
tests/test_hdao_events.py
tests/test_hx_wallet_api.py
tests/test_price_feeder.py
hdao_python_sdk-1.0.1b4.dist-info/LICENSE
hdao_python_sdk-1.0.1b4.dist-info/METADATA
hdao_python_sdk-1.0.1b4.dist-info/WHEEL
hdao_python_sdk-1.0.1b4.dist-info/top_level.txt
hdao_python_sdk-1.0.1b4.dist-info/RECORD
